endaq/calc/__init__.py
endaq/calc/filters.py
endaq/calc/integrate.py
endaq/calc/psd.py
endaq/calc/shock.py
endaq/calc/stats.py
endaq/calc/utils.py
endaq_calc-1.1.0.post2.dist-info/LICENSE
endaq_calc-1.1.0.post2.dist-info/METADATA
endaq_calc-1.1.0.post2.dist-info/WHEEL
endaq_calc-1.1.0.post2.dist-info/top_level.txt
endaq_calc-1.1.0.post2.dist-info/RECORD
