Metadata-Version: 2.1
Name: endaq-calc
Version: 1.1.0.post2
Summary: a computational backend for vibration analysis
Home-page: https://github.com/MideTechnology/endaq-python-calc
Author: Mide Technology
Author-email: help@mide.com
License: MIT
Keywords: ebml binary ide mide endaq
Platform: UNKNOWN
Classifier: Development Status :: 4 - Beta
Classifier: License :: OSI Approved :: MIT License
Classifier: Natural Language :: English
Classifier: Programming Language :: Python :: 3.7
Classifier: Programming Language :: Python :: 3.8
Classifier: Programming Language :: Python :: 3.9
Classifier: Topic :: Scientific/Engineering
License-File: LICENSE
Requires-Dist: numpy (>=1.18)
Requires-Dist: pandas (>=1.2)
Requires-Dist: scipy (>=1.6)
Provides-Extra: example
Requires-Dist: numpy (>=1.18) ; extra == 'example'
Requires-Dist: pandas (>=1.2) ; extra == 'example'
Requires-Dist: scipy (>=1.6) ; extra == 'example'
Provides-Extra: test
Requires-Dist: numpy (>=1.18) ; extra == 'test'
Requires-Dist: pandas (>=1.2) ; extra == 'test'
Requires-Dist: scipy (>=1.6) ; extra == 'test'
Requires-Dist: pytest ; extra == 'test'
Requires-Dist: pytest-cov ; extra == 'test'
Requires-Dist: hypothesis ; extra == 'test'
Requires-Dist: sympy ; extra == 'test'
